anyrun/__init__.py
anyrun/_version.py
anyrun/client.py
anyrun/config.py
anyrun/constants.py
anyrun/exceptions.py
anyrun/sandbox/__init__.py
anyrun/sandbox/base.py
anyrun/sandbox/config.py
anyrun/sandbox/constants.py
anyrun/sandbox/schemas.py
anyrun/sandbox/v1/__init__.py
anyrun/sandbox/v1/client.py
anyrun/sandbox/v1/endpoints.py
anyrun/sandbox/v1/models/__init__.py
anyrun/sandbox/v1/models/analysis.py
anyrun/sandbox/v1/models/common.py
anyrun/sandbox/v1/models/environment.py
anyrun/sandbox/v1/models/request_types.py
anyrun/sandbox/v1/models/response_types.py
anyrun/sandbox/v1/models/task_status_update.py
anyrun/sandbox/v1/models/user.py
anyrun/types.py
anyrun/utils/__init__.py
anyrun/utils/cache.py
anyrun/utils/rate_limit.py
anyrun/utils/retry.py
anyrun/utils/validation.py
anyrun_tools-0.1.2.dist-info/LICENSE
anyrun_tools-0.1.2.dist-info/METADATA
anyrun_tools-0.1.2.dist-info/WHEEL
anyrun_tools-0.1.2.dist-info/RECORD
