Metadata-Version: 2.3
Name: anyrun-tools
Version: 0.1.2
Summary: Python SDK for ANY.RUN APIs
License: MIT
Author: Kirill Bykov
Author-email: bykovk@anyrun.tools
Requires-Python: >=3.8, !=2.7.*, !=3.0.*, !=3.1.*, !=3.2.*, !=3.3.*, !=3.4.*, !=3.5.*, !=3.6.*, !=3.7.*, !=3.12.*, !=3.13.*
Classifier: License :: OSI Approved :: MIT License
Classifier: Programming Language :: Python :: 3
Classifier: Programming Language :: Python :: 3.10
Classifier: Programming Language :: Python :: 3.11
Requires-Dist: cryptography (>=44.0.1,<45.0.0)
Requires-Dist: eval-type-backport (>=0.1.0,<1.0.0)
Requires-Dist: httpx (>=0.25.2,<0.26.0)
Requires-Dist: loguru (>=0.7.2,<0.8.0)
Requires-Dist: pydantic (>=2.5.2,<3.0.0)
Requires-Dist: redis (>=5.0.0,<6.0.0)
Requires-Dist: tenacity (>=8.2.0,<9.0.0)
Requires-Dist: tomli (>=2.0.0,<3.0.0)
Requires-Dist: typing-extensions (>=4.5.0,<5.0.0)
